reflex_image_zoom/__init__.py
reflex_image_zoom/image_zoom.py
reflex_image_zoom-0.0.1.dist-info/METADATA
reflex_image_zoom-0.0.1.dist-info/WHEEL
reflex_image_zoom-0.0.1.dist-info/top_level.txt
reflex_image_zoom-0.0.1.dist-info/RECORD
