Metadata-Version: 2.1
Name: reflex-image-zoom
Version: 0.0.1
Summary: Reflex custom component image-zoom
Author-email: Nikhil Rao <nikhil@reflex.dev>
License: Apache-2.0
Project-URL: Homepage, https://github.com/picklelo/reflex-image-zoom
Keywords: reflex,reflex-custom-components
Classifier: Development Status :: 4 - Beta
Requires-Python: >=3.8
Requires-Dist: reflex >=0.4.2
Provides-Extra: dev
Requires-Dist: build ; extra == 'dev'
Requires-Dist: twine ; extra == 'dev'
